autora/experimentalist/leverage/__init__.py
autora_experimentalist_leverage-1.10.dist-info/LICENSE
autora_experimentalist_leverage-1.10.dist-info/METADATA
autora_experimentalist_leverage-1.10.dist-info/WHEEL
autora_experimentalist_leverage-1.10.dist-info/top_level.txt
autora_experimentalist_leverage-1.10.dist-info/RECORD
