Metadata-Version: 2.1
Name: autora-experimentalist-leverage
Version: 1.10
Summary: Experimentalist that uses statistical leverage to determine the next data to sample.
Author-email: Chad Williams <chad_williams@brown.edu>
License: MIT License
Project-URL: homepage, http://www.empiricalresearch.ai
Project-URL: repository, https://github.com/AutoResearch/autora-experimentalist-leverage
Project-URL: documentation, https://autoresearch.github.io/autora/
Requires-Python: <4,>=3.8
License-File: LICENSE
Requires-Dist: autora-core >=3.1.0
Requires-Dist: scikit-learn
Provides-Extra: dev
Requires-Dist: autora-core[dev] ; extra == 'dev'
